{
    "prices": {
        "gold": 4061.55,
        "silver": 51.31,
        "platinum": 1521.23,
        "palladium": 1334.3517105588,
        "copper": 0.3149459746,
        "binancecoin": 1270.97,
        "bitcoin": 123628,
        "ethereum": 4407.22,
        "solana": 225.4,
        "ripple": 2.82,
        "cardano": 0.815976,
        "dogecoin": 0.249763
    },
    "last_updated": "2025-10-09T13:15:37+00:00",
    "timestamp": 1760015737,
    "status": "success",
    "market_status": {
        "metals_open": true,
        "next_metal_open": "2025-10-09T13:15:37+00:00"
    }
}