{
    "prices": {
        "gold": 4441.93,
        "silver": 74.49,
        "platinum": 1776.1,
        "palladium": 1334.3517105588,
        "copper": 0.3149459746,
        "binancecoin": 650.09,
        "bitcoin": 66296,
        "ethereum": 1844.95,
        "solana": 73.06,
        "ripple": 1.21,
        "cardano": 0.212767,
        "dogecoin": 0.091635
    },
    "last_updated": "2026-06-02T23:30:37+00:00",
    "timestamp": 1780443037,
    "status": "success",
    "market_status": {
        "metals_open": true,
        "next_metal_open": "2026-06-02T23:30:37+00:00"
    }
}