{
    "prices": {
        "gold": 4048,
        "silver": 58.64,
        "platinum": 1478.14,
        "palladium": 1334.3517105588,
        "copper": 0.3149459746,
        "binancecoin": 552.75,
        "bitcoin": 60101,
        "ethereum": 1582.04,
        "solana": 72.73,
        "ripple": 1.052,
        "cardano": 0.145447,
        "dogecoin": 0.073266
    },
    "last_updated": "2026-06-29T06:30:38+00:00",
    "timestamp": 1782714638,
    "status": "success",
    "market_status": {
        "metals_open": true,
        "next_metal_open": "2026-06-29T06:30:38+00:00"
    }
}