{
    "prices": {
        "gold": 4267.91,
        "silver": 63.21,
        "platinum": 1558.66,
        "palladium": 1334.3517105588,
        "copper": 0.3149459746,
        "binancecoin": 885.72,
        "bitcoin": 92507,
        "ethereum": 3241.25,
        "solana": 136.4,
        "ripple": 2.04,
        "cardano": 0.42558,
        "dogecoin": 0.140431
    },
    "last_updated": "2025-12-12T00:00:41+00:00",
    "timestamp": 1765497641,
    "status": "success",
    "market_status": {
        "metals_open": true,
        "next_metal_open": "2025-12-12T00:00:41+00:00"
    }
}