{
    "prices": {
        "gold": 4498.22,
        "silver": 70.3,
        "platinum": 1731.3,
        "palladium": 1334.3517105588,
        "copper": 0.3149459746,
        "binancecoin": 611.45,
        "bitcoin": 66772,
        "ethereum": 2043.84,
        "solana": 82.97,
        "ripple": 1.33,
        "cardano": 0.244825,
        "dogecoin": 0.091341
    },
    "last_updated": "2026-03-30T22:30:37+00:00",
    "timestamp": 1774909837,
    "status": "success",
    "market_status": {
        "metals_open": true,
        "next_metal_open": "2026-03-30T22:30:37+00:00"
    }
}