{
    "data": [
        {
            "timestamp": 1771114537,
            "date": "2026-02-15T00:15:37+00:00",
            "price": 1887.23
        },
        {
            "timestamp": 1771115438,
            "date": "2026-02-15T00:30:38+00:00",
            "price": 1887.23
        },
        {
            "timestamp": 1771116336,
            "date": "2026-02-15T00:45:36+00:00",
            "price": 1887.23
        },
        {
            "timestamp": 1771117236,
            "date": "2026-02-15T01:00:36+00:00",
            "price": 1887.23
        },
        {
            "timestamp": 1771118137,
            "date": "2026-02-15T01:15:37+00:00",
            "price": 1887.23
        },
        {
            "timestamp": 1771119037,
            "date": "2026-02-15T01:30:37+00:00",
            "price": 1887.23
        },
        {
            "timestamp": 1771119937,
            "date": "2026-02-15T01:45:37+00:00",
            "price": 1887.23
        },
        {
            "timestamp": 1771120837,
            "date": "2026-02-15T02:00:37+00:00",
            "price": 1887.23
        },
        {
            "timestamp": 1771121737,
            "date": "2026-02-15T02:15:37+00:00",
            "price": 1887.23
        },
        {
            "timestamp": 1771122637,
            "date": "2026-02-15T02:30:37+00:00",
            "price": 1887.23
        },
        {
            "timestamp": 1771123536,
            "date": "2026-02-15T02:45:36+00:00",
            "price": 1887.23
        },
        {
            "timestamp": 1771124437,
            "date": "2026-02-15T03:00:37+00:00",
            "price": 1887.23
        },
        {
            "timestamp": 1771125337,
            "date": "2026-02-15T03:15:37+00:00",
            "price": 1887.23
        },
        {
            "timestamp": 1771126237,
            "date": "2026-02-15T03:30:37+00:00",
            "price": 1887.23
        },
        {
            "timestamp": 1771127139,
            "date": "2026-02-15T03:45:39+00:00",
            "price": 1887.23
        },
        {
            "timestamp": 1771128039,
            "date": "2026-02-15T04:00:39+00:00",
            "price": 1887.23
        },
        {
            "timestamp": 1771128936,
            "date": "2026-02-15T04:15:36+00:00",
            "price": 1887.23
        },
        {
            "timestamp": 1771129837,
            "date": "2026-02-15T04:30:37+00:00",
            "price": 1887.23
        },
        {
            "timestamp": 1771130737,
            "date": "2026-02-15T04:45:37+00:00",
            "price": 1887.23
        },
        {
            "timestamp": 1771131637,
            "date": "2026-02-15T05:00:37+00:00",
            "price": 1887.23
        },
        {
            "timestamp": 1771132537,
            "date": "2026-02-15T05:15:37+00:00",
            "price": 1887.23
        },
        {
            "timestamp": 1771133437,
            "date": "2026-02-15T05:30:37+00:00",
            "price": 1887.23
        },
        {
            "timestamp": 1771134336,
            "date": "2026-02-15T05:45:36+00:00",
            "price": 1887.23
        },
        {
            "timestamp": 1771135237,
            "date": "2026-02-15T06:00:37+00:00",
            "price": 1887.23
        },
        {
            "timestamp": 1771136137,
            "date": "2026-02-15T06:15:37+00:00",
            "price": 1887.23
        },
        {
            "timestamp": 1771137037,
            "date": "2026-02-15T06:30:37+00:00",
            "price": 1887.23
        },
        {
            "timestamp": 1771137936,
            "date": "2026-02-15T06:45:36+00:00",
            "price": 1887.23
        },
        {
            "timestamp": 1771138837,
            "date": "2026-02-15T07:00:37+00:00",
            "price": 1887.23
        },
        {
            "timestamp": 1771139736,
            "date": "2026-02-15T07:15:36+00:00",
            "price": 1887.23
        },
        {
            "timestamp": 1771140637,
            "date": "2026-02-15T07:30:37+00:00",
            "price": 1887.23
        },
        {
            "timestamp": 1771141536,
            "date": "2026-02-15T07:45:36+00:00",
            "price": 1887.23
        },
        {
            "timestamp": 1771142437,
            "date": "2026-02-15T08:00:37+00:00",
            "price": 1887.23
        },
        {
            "timestamp": 1771143337,
            "date": "2026-02-15T08:15:37+00:00",
            "price": 1887.23
        },
        {
            "timestamp": 1771144237,
            "date": "2026-02-15T08:30:37+00:00",
            "price": 1887.23
        },
        {
            "timestamp": 1771145137,
            "date": "2026-02-15T08:45:37+00:00",
            "price": 1887.23
        },
        {
            "timestamp": 1771146037,
            "date": "2026-02-15T09:00:37+00:00",
            "price": 1887.23
        },
        {
            "timestamp": 1771146937,
            "date": "2026-02-15T09:15:37+00:00",
            "price": 1887.23
        },
        {
            "timestamp": 1771147838,
            "date": "2026-02-15T09:30:38+00:00",
            "price": 1887.23
        },
        {
            "timestamp": 1771148736,
            "date": "2026-02-15T09:45:36+00:00",
            "price": 1887.23
        },
        {
            "timestamp": 1771149637,
            "date": "2026-02-15T10:00:37+00:00",
            "price": 1887.23
        },
        {
            "timestamp": 1771150537,
            "date": "2026-02-15T10:15:37+00:00",
            "price": 1887.23
        },
        {
            "timestamp": 1771151437,
            "date": "2026-02-15T10:30:37+00:00",
            "price": 1887.23
        },
        {
            "timestamp": 1771152336,
            "date": "2026-02-15T10:45:36+00:00",
            "price": 1887.23
        },
        {
            "timestamp": 1771153237,
            "date": "2026-02-15T11:00:37+00:00",
            "price": 1887.23
        },
        {
            "timestamp": 1771154137,
            "date": "2026-02-15T11:15:37+00:00",
            "price": 1887.23
        },
        {
            "timestamp": 1771155036,
            "date": "2026-02-15T11:30:36+00:00",
            "price": 1887.23
        },
        {
            "timestamp": 1771155937,
            "date": "2026-02-15T11:45:37+00:00",
            "price": 1887.23
        },
        {
            "timestamp": 1771156837,
            "date": "2026-02-15T12:00:37+00:00",
            "price": 1887.23
        },
        {
            "timestamp": 1771157737,
            "date": "2026-02-15T12:15:37+00:00",
            "price": 1887.23
        },
        {
            "timestamp": 1771158637,
            "date": "2026-02-15T12:30:37+00:00",
            "price": 1887.23
        },
        {
            "timestamp": 1771159537,
            "date": "2026-02-15T12:45:37+00:00",
            "price": 1887.23
        },
        {
            "timestamp": 1771160438,
            "date": "2026-02-15T13:00:38+00:00",
            "price": 1887.23
        },
        {
            "timestamp": 1771161337,
            "date": "2026-02-15T13:15:37+00:00",
            "price": 1887.23
        },
        {
            "timestamp": 1771162237,
            "date": "2026-02-15T13:30:37+00:00",
            "price": 1887.23
        },
        {
            "timestamp": 1771163137,
            "date": "2026-02-15T13:45:37+00:00",
            "price": 1887.23
        },
        {
            "timestamp": 1771164037,
            "date": "2026-02-15T14:00:37+00:00",
            "price": 1887.23
        },
        {
            "timestamp": 1771164937,
            "date": "2026-02-15T14:15:37+00:00",
            "price": 1887.23
        },
        {
            "timestamp": 1771165837,
            "date": "2026-02-15T14:30:37+00:00",
            "price": 1887.23
        },
        {
            "timestamp": 1771166737,
            "date": "2026-02-15T14:45:37+00:00",
            "price": 1887.23
        },
        {
            "timestamp": 1771167637,
            "date": "2026-02-15T15:00:37+00:00",
            "price": 1887.23
        },
        {
            "timestamp": 1771168536,
            "date": "2026-02-15T15:15:36+00:00",
            "price": 1887.23
        },
        {
            "timestamp": 1771169437,
            "date": "2026-02-15T15:30:37+00:00",
            "price": 1887.23
        },
        {
            "timestamp": 1771170337,
            "date": "2026-02-15T15:45:37+00:00",
            "price": 1887.23
        },
        {
            "timestamp": 1771171237,
            "date": "2026-02-15T16:00:37+00:00",
            "price": 1887.23
        },
        {
            "timestamp": 1771172137,
            "date": "2026-02-15T16:15:37+00:00",
            "price": 1887.23
        },
        {
            "timestamp": 1771173037,
            "date": "2026-02-15T16:30:37+00:00",
            "price": 1887.23
        },
        {
            "timestamp": 1771173937,
            "date": "2026-02-15T16:45:37+00:00",
            "price": 1887.23
        },
        {
            "timestamp": 1771174837,
            "date": "2026-02-15T17:00:37+00:00",
            "price": 1887.23
        },
        {
            "timestamp": 1771175737,
            "date": "2026-02-15T17:15:37+00:00",
            "price": 1887.23
        },
        {
            "timestamp": 1771176637,
            "date": "2026-02-15T17:30:37+00:00",
            "price": 1887.23
        },
        {
            "timestamp": 1771177537,
            "date": "2026-02-15T17:45:37+00:00",
            "price": 1887.23
        },
        {
            "timestamp": 1771178438,
            "date": "2026-02-15T18:00:38+00:00",
            "price": 1887.23
        },
        {
            "timestamp": 1771179337,
            "date": "2026-02-15T18:15:37+00:00",
            "price": 1887.23
        },
        {
            "timestamp": 1771180238,
            "date": "2026-02-15T18:30:38+00:00",
            "price": 1887.23
        },
        {
            "timestamp": 1771181137,
            "date": "2026-02-15T18:45:37+00:00",
            "price": 1887.23
        },
        {
            "timestamp": 1771182036,
            "date": "2026-02-15T19:00:36+00:00",
            "price": 1887.23
        },
        {
            "timestamp": 1771182937,
            "date": "2026-02-15T19:15:37+00:00",
            "price": 1887.23
        },
        {
            "timestamp": 1771183837,
            "date": "2026-02-15T19:30:37+00:00",
            "price": 1887.23
        },
        {
            "timestamp": 1771184737,
            "date": "2026-02-15T19:45:37+00:00",
            "price": 1887.23
        },
        {
            "timestamp": 1771185637,
            "date": "2026-02-15T20:00:37+00:00",
            "price": 1887.23
        },
        {
            "timestamp": 1771186536,
            "date": "2026-02-15T20:15:36+00:00",
            "price": 1887.23
        },
        {
            "timestamp": 1771187437,
            "date": "2026-02-15T20:30:37+00:00",
            "price": 1887.23
        },
        {
            "timestamp": 1771188337,
            "date": "2026-02-15T20:45:37+00:00",
            "price": 1887.23
        },
        {
            "timestamp": 1771189237,
            "date": "2026-02-15T21:00:37+00:00",
            "price": 1887.23
        },
        {
            "timestamp": 1771190138,
            "date": "2026-02-15T21:15:38+00:00",
            "price": 1887.23
        },
        {
            "timestamp": 1771191036,
            "date": "2026-02-15T21:30:36+00:00",
            "price": 1887.23
        },
        {
            "timestamp": 1771191937,
            "date": "2026-02-15T21:45:37+00:00",
            "price": 1887.23
        },
        {
            "timestamp": 1771192837,
            "date": "2026-02-15T22:00:37+00:00",
            "price": 1887.23
        },
        {
            "timestamp": 1771193737,
            "date": "2026-02-15T22:15:37+00:00",
            "price": 1887.23
        },
        {
            "timestamp": 1771194636,
            "date": "2026-02-15T22:30:36+00:00",
            "price": 1887.23
        },
        {
            "timestamp": 1771195537,
            "date": "2026-02-15T22:45:37+00:00",
            "price": 1887.23
        },
        {
            "timestamp": 1771196437,
            "date": "2026-02-15T23:00:37+00:00",
            "price": 1897.72
        },
        {
            "timestamp": 1771197337,
            "date": "2026-02-15T23:15:37+00:00",
            "price": 1897.72
        },
        {
            "timestamp": 1771198237,
            "date": "2026-02-15T23:30:37+00:00",
            "price": 1890.06
        },
        {
            "timestamp": 1771199137,
            "date": "2026-02-15T23:45:37+00:00",
            "price": 1888.36
        },
        {
            "timestamp": 1771200069,
            "date": "2026-02-16T00:01:09+00:00",
            "price": 1885.81
        },
        {
            "timestamp": 1771200938,
            "date": "2026-02-16T00:15:38+00:00",
            "price": 1887.51
        },
        {
            "timestamp": 1771201838,
            "date": "2026-02-16T00:30:38+00:00",
            "price": 1888.36
        },
        {
            "timestamp": 1771202737,
            "date": "2026-02-16T00:45:37+00:00",
            "price": 1886.94
        },
        {
            "timestamp": 1771203637,
            "date": "2026-02-16T01:00:37+00:00",
            "price": 1886.94
        },
        {
            "timestamp": 1771204537,
            "date": "2026-02-16T01:15:37+00:00",
            "price": 1888.93
        },
        {
            "timestamp": 1771205437,
            "date": "2026-02-16T01:30:37+00:00",
            "price": 1887.51
        },
        {
            "timestamp": 1771206337,
            "date": "2026-02-16T01:45:37+00:00",
            "price": 1887.23
        },
        {
            "timestamp": 1771207237,
            "date": "2026-02-16T02:00:37+00:00",
            "price": 1886.09
        },
        {
            "timestamp": 1771208137,
            "date": "2026-02-16T02:15:37+00:00",
            "price": 1888.08
        },
        {
            "timestamp": 1771209037,
            "date": "2026-02-16T02:30:37+00:00",
            "price": 1887.79
        },
        {
            "timestamp": 1771209937,
            "date": "2026-02-16T02:45:37+00:00",
            "price": 1888.93
        },
        {
            "timestamp": 1771210837,
            "date": "2026-02-16T03:00:37+00:00",
            "price": 1889.49
        },
        {
            "timestamp": 1771211737,
            "date": "2026-02-16T03:15:37+00:00",
            "price": 1888.08
        },
        {
            "timestamp": 1771212637,
            "date": "2026-02-16T03:30:37+00:00",
            "price": 1889.21
        },
        {
            "timestamp": 1771213537,
            "date": "2026-02-16T03:45:37+00:00",
            "price": 1888.36
        },
        {
            "timestamp": 1771214437,
            "date": "2026-02-16T04:00:37+00:00",
            "price": 1886.09
        },
        {
            "timestamp": 1771215337,
            "date": "2026-02-16T04:15:37+00:00",
            "price": 1884.96
        },
        {
            "timestamp": 1771216237,
            "date": "2026-02-16T04:30:37+00:00",
            "price": 1884.96
        },
        {
            "timestamp": 1771217137,
            "date": "2026-02-16T04:45:37+00:00",
            "price": 1870.78
        },
        {
            "timestamp": 1771218038,
            "date": "2026-02-16T05:00:38+00:00",
            "price": 1875.32
        },
        {
            "timestamp": 1771218937,
            "date": "2026-02-16T05:15:37+00:00",
            "price": 1863.98
        },
        {
            "timestamp": 1771219837,
            "date": "2026-02-16T05:30:37+00:00",
            "price": 1873.33
        },
        {
            "timestamp": 1771220737,
            "date": "2026-02-16T05:45:37+00:00",
            "price": 1870.22
        },
        {
            "timestamp": 1771221638,
            "date": "2026-02-16T06:00:38+00:00",
            "price": 1878.15
        },
        {
            "timestamp": 1771222537,
            "date": "2026-02-16T06:15:37+00:00",
            "price": 1886.94
        },
        {
            "timestamp": 1771223438,
            "date": "2026-02-16T06:30:38+00:00",
            "price": 1879.29
        },
        {
            "timestamp": 1771224337,
            "date": "2026-02-16T06:45:37+00:00",
            "price": 1879.29
        },
        {
            "timestamp": 1771225238,
            "date": "2026-02-16T07:00:38+00:00",
            "price": 1881.56
        },
        {
            "timestamp": 1771226136,
            "date": "2026-02-16T07:15:36+00:00",
            "price": 1874.47
        },
        {
            "timestamp": 1771227037,
            "date": "2026-02-16T07:30:37+00:00",
            "price": 1873.33
        },
        {
            "timestamp": 1771227937,
            "date": "2026-02-16T07:45:37+00:00",
            "price": 1875.32
        },
        {
            "timestamp": 1771228838,
            "date": "2026-02-16T08:00:38+00:00",
            "price": 1875.04
        },
        {
            "timestamp": 1771229737,
            "date": "2026-02-16T08:15:37+00:00",
            "price": 1874.75
        },
        {
            "timestamp": 1771230638,
            "date": "2026-02-16T08:30:38+00:00",
            "price": 1874.75
        },
        {
            "timestamp": 1771231537,
            "date": "2026-02-16T08:45:37+00:00",
            "price": 1873.9
        },
        {
            "timestamp": 1771232438,
            "date": "2026-02-16T09:00:38+00:00",
            "price": 1874.75
        },
        {
            "timestamp": 1771233337,
            "date": "2026-02-16T09:15:37+00:00",
            "price": 1873.33
        },
        {
            "timestamp": 1771234237,
            "date": "2026-02-16T09:30:37+00:00",
            "price": 1873.33
        },
        {
            "timestamp": 1771235137,
            "date": "2026-02-16T09:45:37+00:00",
            "price": 1875.6
        },
        {
            "timestamp": 1771236037,
            "date": "2026-02-16T10:00:37+00:00",
            "price": 1873.9
        },
        {
            "timestamp": 1771236937,
            "date": "2026-02-16T10:15:37+00:00",
            "price": 1874.19
        },
        {
            "timestamp": 1771237837,
            "date": "2026-02-16T10:30:37+00:00",
            "price": 1875.04
        },
        {
            "timestamp": 1771238737,
            "date": "2026-02-16T10:45:37+00:00",
            "price": 1874.47
        },
        {
            "timestamp": 1771239637,
            "date": "2026-02-16T11:00:37+00:00",
            "price": 1874.47
        },
        {
            "timestamp": 1771240537,
            "date": "2026-02-16T11:15:37+00:00",
            "price": 1863.98
        },
        {
            "timestamp": 1771241437,
            "date": "2026-02-16T11:30:37+00:00",
            "price": 1861.14
        },
        {
            "timestamp": 1771242337,
            "date": "2026-02-16T11:45:37+00:00",
            "price": 1860.86
        },
        {
            "timestamp": 1771243238,
            "date": "2026-02-16T12:00:38+00:00",
            "price": 1860.58
        },
        {
            "timestamp": 1771244137,
            "date": "2026-02-16T12:15:37+00:00",
            "price": 1860.86
        },
        {
            "timestamp": 1771245037,
            "date": "2026-02-16T12:30:37+00:00",
            "price": 1860.58
        },
        {
            "timestamp": 1771245937,
            "date": "2026-02-16T12:45:37+00:00",
            "price": 1861.14
        },
        {
            "timestamp": 1771246837,
            "date": "2026-02-16T13:00:37+00:00",
            "price": 1860.86
        },
        {
            "timestamp": 1771247737,
            "date": "2026-02-16T13:15:37+00:00",
            "price": 1860.86
        },
        {
            "timestamp": 1771248637,
            "date": "2026-02-16T13:30:37+00:00",
            "price": 1863.13
        },
        {
            "timestamp": 1771249537,
            "date": "2026-02-16T13:45:37+00:00",
            "price": 1864.83
        },
        {
            "timestamp": 1771250437,
            "date": "2026-02-16T14:00:37+00:00",
            "price": 1860.29
        },
        {
            "timestamp": 1771251338,
            "date": "2026-02-16T14:15:38+00:00",
            "price": 1860.29
        },
        {
            "timestamp": 1771252237,
            "date": "2026-02-16T14:30:37+00:00",
            "price": 1860.01
        },
        {
            "timestamp": 1771253137,
            "date": "2026-02-16T14:45:37+00:00",
            "price": 1860.01
        },
        {
            "timestamp": 1771254038,
            "date": "2026-02-16T15:00:38+00:00",
            "price": 1862.85
        },
        {
            "timestamp": 1771254937,
            "date": "2026-02-16T15:15:37+00:00",
            "price": 1860.01
        },
        {
            "timestamp": 1771255837,
            "date": "2026-02-16T15:30:37+00:00",
            "price": 1860.01
        },
        {
            "timestamp": 1771256737,
            "date": "2026-02-16T15:45:37+00:00",
            "price": 1865.4
        },
        {
            "timestamp": 1771257638,
            "date": "2026-02-16T16:00:38+00:00",
            "price": 1863.98
        },
        {
            "timestamp": 1771258537,
            "date": "2026-02-16T16:15:37+00:00",
            "price": 1856.89
        },
        {
            "timestamp": 1771259437,
            "date": "2026-02-16T16:30:37+00:00",
            "price": 1857.18
        },
        {
            "timestamp": 1771260337,
            "date": "2026-02-16T16:45:37+00:00",
            "price": 1852.92
        },
        {
            "timestamp": 1771261237,
            "date": "2026-02-16T17:00:37+00:00",
            "price": 1857.74
        },
        {
            "timestamp": 1771262137,
            "date": "2026-02-16T17:15:37+00:00",
            "price": 1855.19
        },
        {
            "timestamp": 1771263038,
            "date": "2026-02-16T17:30:38+00:00",
            "price": 1858.03
        },
        {
            "timestamp": 1771263937,
            "date": "2026-02-16T17:45:37+00:00",
            "price": 1857.46
        },
        {
            "timestamp": 1771264838,
            "date": "2026-02-16T18:00:38+00:00",
            "price": 1856.33
        },
        {
            "timestamp": 1771265737,
            "date": "2026-02-16T18:15:37+00:00",
            "price": 1856.04
        },
        {
            "timestamp": 1771266638,
            "date": "2026-02-16T18:30:38+00:00",
            "price": 1865.96
        },
        {
            "timestamp": 1771267537,
            "date": "2026-02-16T18:45:37+00:00",
            "price": 1871.07
        },
        {
            "timestamp": 1771268438,
            "date": "2026-02-16T19:00:38+00:00",
            "price": 1865.96
        },
        {
            "timestamp": 1771269338,
            "date": "2026-02-16T19:15:38+00:00",
            "price": 1867.67
        },
        {
            "timestamp": 1771270237,
            "date": "2026-02-16T19:30:37+00:00",
            "price": 1868.52
        },
        {
            "timestamp": 1771271138,
            "date": "2026-02-16T19:45:38+00:00",
            "price": 1863.41
        },
        {
            "timestamp": 1771272037,
            "date": "2026-02-16T20:00:37+00:00",
            "price": 1870.22
        },
        {
            "timestamp": 1771272938,
            "date": "2026-02-16T20:15:38+00:00",
            "price": 1866.81
        },
        {
            "timestamp": 1771273837,
            "date": "2026-02-16T20:30:37+00:00",
            "price": 1870.22
        },
        {
            "timestamp": 1771274737,
            "date": "2026-02-16T20:45:37+00:00",
            "price": 1868.8
        },
        {
            "timestamp": 1771275638,
            "date": "2026-02-16T21:00:38+00:00",
            "price": 1872.2
        },
        {
            "timestamp": 1771276537,
            "date": "2026-02-16T21:15:37+00:00",
            "price": 1870.22
        },
        {
            "timestamp": 1771277437,
            "date": "2026-02-16T21:30:37+00:00",
            "price": 1874.47
        },
        {
            "timestamp": 1771278337,
            "date": "2026-02-16T21:45:37+00:00",
            "price": 1868.8
        },
        {
            "timestamp": 1771279237,
            "date": "2026-02-16T22:00:37+00:00",
            "price": 1869.65
        },
        {
            "timestamp": 1771280137,
            "date": "2026-02-16T22:15:37+00:00",
            "price": 1863.98
        },
        {
            "timestamp": 1771281038,
            "date": "2026-02-16T22:30:38+00:00",
            "price": 1862
        },
        {
            "timestamp": 1771281937,
            "date": "2026-02-16T22:45:37+00:00",
            "price": 1869.37
        },
        {
            "timestamp": 1771282837,
            "date": "2026-02-16T23:00:37+00:00",
            "price": 1870.5
        },
        {
            "timestamp": 1771283737,
            "date": "2026-02-16T23:15:37+00:00",
            "price": 1871.07
        },
        {
            "timestamp": 1771284637,
            "date": "2026-02-16T23:30:37+00:00",
            "price": 1870.5
        },
        {
            "timestamp": 1771285537,
            "date": "2026-02-16T23:45:37+00:00",
            "price": 1873.05
        },
        {
            "timestamp": 1771286470,
            "date": "2026-02-17T00:01:10+00:00",
            "price": 1869.65
        },
        {
            "timestamp": 1771287337,
            "date": "2026-02-17T00:15:37+00:00",
            "price": 1861.43
        },
        {
            "timestamp": 1771288238,
            "date": "2026-02-17T00:30:38+00:00",
            "price": 1861.43
        },
        {
            "timestamp": 1771289138,
            "date": "2026-02-17T00:45:38+00:00",
            "price": 1865.96
        },
        {
            "timestamp": 1771290038,
            "date": "2026-02-17T01:00:38+00:00",
            "price": 1859.73
        },
        {
            "timestamp": 1771290937,
            "date": "2026-02-17T01:15:37+00:00",
            "price": 1861.14
        },
        {
            "timestamp": 1771291837,
            "date": "2026-02-17T01:30:37+00:00",
            "price": 1861.71
        },
        {
            "timestamp": 1771292739,
            "date": "2026-02-17T01:45:39+00:00",
            "price": 1864.83
        },
        {
            "timestamp": 1771293637,
            "date": "2026-02-17T02:00:37+00:00",
            "price": 1863.98
        },
        {
            "timestamp": 1771294537,
            "date": "2026-02-17T02:15:37+00:00",
            "price": 1865.4
        },
        {
            "timestamp": 1771295437,
            "date": "2026-02-17T02:30:37+00:00",
            "price": 1863.13
        },
        {
            "timestamp": 1771296337,
            "date": "2026-02-17T02:45:37+00:00",
            "price": 1865.68
        },
        {
            "timestamp": 1771297237,
            "date": "2026-02-17T03:00:37+00:00",
            "price": 1861.43
        },
        {
            "timestamp": 1771298137,
            "date": "2026-02-17T03:15:37+00:00",
            "price": 1864.55
        },
        {
            "timestamp": 1771299037,
            "date": "2026-02-17T03:30:37+00:00",
            "price": 1865.11
        },
        {
            "timestamp": 1771299937,
            "date": "2026-02-17T03:45:37+00:00",
            "price": 1859.16
        },
        {
            "timestamp": 1771300837,
            "date": "2026-02-17T04:00:37+00:00",
            "price": 1859.44
        },
        {
            "timestamp": 1771301737,
            "date": "2026-02-17T04:15:37+00:00",
            "price": 1860.01
        },
        {
            "timestamp": 1771302637,
            "date": "2026-02-17T04:30:37+00:00",
            "price": 1859.44
        },
        {
            "timestamp": 1771303537,
            "date": "2026-02-17T04:45:37+00:00",
            "price": 1860.86
        },
        {
            "timestamp": 1771304437,
            "date": "2026-02-17T05:00:37+00:00",
            "price": 1858.88
        },
        {
            "timestamp": 1771305337,
            "date": "2026-02-17T05:15:37+00:00",
            "price": 1860.29
        },
        {
            "timestamp": 1771306237,
            "date": "2026-02-17T05:30:37+00:00",
            "price": 1828.54
        },
        {
            "timestamp": 1771307137,
            "date": "2026-02-17T05:45:37+00:00",
            "price": 1834.5
        },
        {
            "timestamp": 1771308037,
            "date": "2026-02-17T06:00:37+00:00",
            "price": 1832.23
        },
        {
            "timestamp": 1771308937,
            "date": "2026-02-17T06:15:37+00:00",
            "price": 1832.23
        },
        {
            "timestamp": 1771309837,
            "date": "2026-02-17T06:30:37+00:00",
            "price": 1827.98
        },
        {
            "timestamp": 1771310737,
            "date": "2026-02-17T06:45:37+00:00",
            "price": 1836.2
        },
        {
            "timestamp": 1771311638,
            "date": "2026-02-17T07:00:38+00:00",
            "price": 1834.78
        },
        {
            "timestamp": 1771312537,
            "date": "2026-02-17T07:15:37+00:00",
            "price": 1835.35
        },
        {
            "timestamp": 1771313437,
            "date": "2026-02-17T07:30:37+00:00",
            "price": 1838.18
        },
        {
            "timestamp": 1771314337,
            "date": "2026-02-17T07:45:37+00:00",
            "price": 1829.96
        },
        {
            "timestamp": 1771315238,
            "date": "2026-02-17T08:00:38+00:00",
            "price": 1840.17
        },
        {
            "timestamp": 1771316137,
            "date": "2026-02-17T08:15:37+00:00",
            "price": 1840.17
        },
        {
            "timestamp": 1771317037,
            "date": "2026-02-17T08:30:37+00:00",
            "price": 1844.99
        },
        {
            "timestamp": 1771317937,
            "date": "2026-02-17T08:45:37+00:00",
            "price": 1841.3
        },
        {
            "timestamp": 1771318838,
            "date": "2026-02-17T09:00:38+00:00",
            "price": 1845.27
        },
        {
            "timestamp": 1771319737,
            "date": "2026-02-17T09:15:37+00:00",
            "price": 1845.55
        },
        {
            "timestamp": 1771320637,
            "date": "2026-02-17T09:30:37+00:00",
            "price": 1832.8
        },
        {
            "timestamp": 1771321538,
            "date": "2026-02-17T09:45:38+00:00",
            "price": 1831.94
        },
        {
            "timestamp": 1771322438,
            "date": "2026-02-17T10:00:38+00:00",
            "price": 1832.51
        },
        {
            "timestamp": 1771323337,
            "date": "2026-02-17T10:15:37+00:00",
            "price": 1828.26
        },
        {
            "timestamp": 1771324237,
            "date": "2026-02-17T10:30:37+00:00",
            "price": 1833.36
        },
        {
            "timestamp": 1771325137,
            "date": "2026-02-17T10:45:37+00:00",
            "price": 1834.78
        },
        {
            "timestamp": 1771326038,
            "date": "2026-02-17T11:00:38+00:00",
            "price": 1828.54
        },
        {
            "timestamp": 1771326938,
            "date": "2026-02-17T11:15:38+00:00",
            "price": 1826.27
        },
        {
            "timestamp": 1771327837,
            "date": "2026-02-17T11:30:37+00:00",
            "price": 1833.93
        },
        {
            "timestamp": 1771328737,
            "date": "2026-02-17T11:45:37+00:00",
            "price": 1832.23
        },
        {
            "timestamp": 1771329638,
            "date": "2026-02-17T12:00:38+00:00",
            "price": 1818.05
        },
        {
            "timestamp": 1771330538,
            "date": "2026-02-17T12:15:38+00:00",
            "price": 1830.81
        },
        {
            "timestamp": 1771331437,
            "date": "2026-02-17T12:30:37+00:00",
            "price": 1834.78
        },
        {
            "timestamp": 1771332337,
            "date": "2026-02-17T12:45:37+00:00",
            "price": 1845.27
        },
        {
            "timestamp": 1771333237,
            "date": "2026-02-17T13:00:37+00:00",
            "price": 1841.02
        },
        {
            "timestamp": 1771334139,
            "date": "2026-02-17T13:15:39+00:00",
            "price": 1831.94
        },
        {
            "timestamp": 1771335037,
            "date": "2026-02-17T13:30:37+00:00",
            "price": 1837.61
        },
        {
            "timestamp": 1771335937,
            "date": "2026-02-17T13:45:37+00:00",
            "price": 1838.18
        },
        {
            "timestamp": 1771336837,
            "date": "2026-02-17T14:00:37+00:00",
            "price": 1848.39
        },
        {
            "timestamp": 1771337737,
            "date": "2026-02-17T14:15:37+00:00",
            "price": 1836.76
        },
        {
            "timestamp": 1771338637,
            "date": "2026-02-17T14:30:37+00:00",
            "price": 1848.39
        },
        {
            "timestamp": 1771339537,
            "date": "2026-02-17T14:45:37+00:00",
            "price": 1846.4
        },
        {
            "timestamp": 1771340438,
            "date": "2026-02-17T15:00:38+00:00",
            "price": 1841.87
        },
        {
            "timestamp": 1771341337,
            "date": "2026-02-17T15:15:37+00:00",
            "price": 1836.48
        },
        {
            "timestamp": 1771342237,
            "date": "2026-02-17T15:30:37+00:00",
            "price": 1841.3
        },
        {
            "timestamp": 1771343137,
            "date": "2026-02-17T15:45:37+00:00",
            "price": 1844.42
        },
        {
            "timestamp": 1771344040,
            "date": "2026-02-17T16:00:40+00:00",
            "price": 1839.32
        },
        {
            "timestamp": 1771344938,
            "date": "2026-02-17T16:15:38+00:00",
            "price": 1847.25
        },
        {
            "timestamp": 1771345837,
            "date": "2026-02-17T16:30:37+00:00",
            "price": 1851.22
        },
        {
            "timestamp": 1771346737,
            "date": "2026-02-17T16:45:37+00:00",
            "price": 1849.24
        },
        {
            "timestamp": 1771347637,
            "date": "2026-02-17T17:00:37+00:00",
            "price": 1850.37
        },
        {
            "timestamp": 1771348537,
            "date": "2026-02-17T17:15:37+00:00",
            "price": 1848.95
        },
        {
            "timestamp": 1771349437,
            "date": "2026-02-17T17:30:37+00:00",
            "price": 1844.13
        },
        {
            "timestamp": 1771350337,
            "date": "2026-02-17T17:45:37+00:00",
            "price": 1844.99
        },
        {
            "timestamp": 1771351237,
            "date": "2026-02-17T18:00:37+00:00",
            "price": 1843
        },
        {
            "timestamp": 1771352137,
            "date": "2026-02-17T18:15:37+00:00",
            "price": 1837.33
        },
        {
            "timestamp": 1771353038,
            "date": "2026-02-17T18:30:38+00:00",
            "price": 1834.21
        },
        {
            "timestamp": 1771353937,
            "date": "2026-02-17T18:45:37+00:00",
            "price": 1831.38
        },
        {
            "timestamp": 1771354837,
            "date": "2026-02-17T19:00:37+00:00",
            "price": 1835.91
        },
        {
            "timestamp": 1771355738,
            "date": "2026-02-17T19:15:38+00:00",
            "price": 1837.33
        },
        {
            "timestamp": 1771356638,
            "date": "2026-02-17T19:30:38+00:00",
            "price": 1837.9
        },
        {
            "timestamp": 1771357537,
            "date": "2026-02-17T19:45:37+00:00",
            "price": 1837.61
        },
        {
            "timestamp": 1771358437,
            "date": "2026-02-17T20:00:37+00:00",
            "price": 1837.61
        },
        {
            "timestamp": 1771359338,
            "date": "2026-02-17T20:15:38+00:00",
            "price": 1838.18
        },
        {
            "timestamp": 1771360238,
            "date": "2026-02-17T20:30:38+00:00",
            "price": 1838.18
        },
        {
            "timestamp": 1771361138,
            "date": "2026-02-17T20:45:38+00:00",
            "price": 1838.75
        },
        {
            "timestamp": 1771362038,
            "date": "2026-02-17T21:00:38+00:00",
            "price": 1837.33
        },
        {
            "timestamp": 1771362937,
            "date": "2026-02-17T21:15:37+00:00",
            "price": 1832.51
        },
        {
            "timestamp": 1771363838,
            "date": "2026-02-17T21:30:38+00:00",
            "price": 1831.94
        },
        {
            "timestamp": 1771364737,
            "date": "2026-02-17T21:45:37+00:00",
            "price": 1833.65
        },
        {
            "timestamp": 1771365645,
            "date": "2026-02-17T22:00:45+00:00",
            "price": 1834.21
        },
        {
            "timestamp": 1771366538,
            "date": "2026-02-17T22:15:38+00:00",
            "price": 1835.63
        },
        {
            "timestamp": 1771367437,
            "date": "2026-02-17T22:30:37+00:00",
            "price": 1834.5
        },
        {
            "timestamp": 1771368337,
            "date": "2026-02-17T22:45:37+00:00",
            "price": 1834.78
        },
        {
            "timestamp": 1771369238,
            "date": "2026-02-17T23:00:38+00:00",
            "price": 1832.23
        },
        {
            "timestamp": 1771370137,
            "date": "2026-02-17T23:15:37+00:00",
            "price": 1835.35
        },
        {
            "timestamp": 1771371037,
            "date": "2026-02-17T23:30:37+00:00",
            "price": 1835.06
        },
        {
            "timestamp": 1771371937,
            "date": "2026-02-17T23:45:37+00:00",
            "price": 1832.51
        },
        {
            "timestamp": 1771372870,
            "date": "2026-02-18T00:01:10+00:00",
            "price": 1832.23
        },
        {
            "timestamp": 1771373738,
            "date": "2026-02-18T00:15:38+00:00",
            "price": 1832.23
        },
        {
            "timestamp": 1771374638,
            "date": "2026-02-18T00:30:38+00:00",
            "price": 1834.21
        },
        {
            "timestamp": 1771375537,
            "date": "2026-02-18T00:45:37+00:00",
            "price": 1838.18
        },
        {
            "timestamp": 1771376437,
            "date": "2026-02-18T01:00:37+00:00",
            "price": 1835.91
        },
        {
            "timestamp": 1771377337,
            "date": "2026-02-18T01:15:37+00:00",
            "price": 1835.35
        },
        {
            "timestamp": 1771378237,
            "date": "2026-02-18T01:30:37+00:00",
            "price": 1840.45
        },
        {
            "timestamp": 1771379136,
            "date": "2026-02-18T01:45:36+00:00",
            "price": 1837.9
        },
        {
            "timestamp": 1771380037,
            "date": "2026-02-18T02:00:37+00:00",
            "price": 1839.88
        },
        {
            "timestamp": 1771380936,
            "date": "2026-02-18T02:15:36+00:00",
            "price": 1855.76
        },
        {
            "timestamp": 1771381837,
            "date": "2026-02-18T02:30:37+00:00",
            "price": 1851.79
        },
        {
            "timestamp": 1771382737,
            "date": "2026-02-18T02:45:37+00:00",
            "price": 1853.77
        },
        {
            "timestamp": 1771383637,
            "date": "2026-02-18T03:00:37+00:00",
            "price": 1855.47
        },
        {
            "timestamp": 1771384537,
            "date": "2026-02-18T03:15:37+00:00",
            "price": 1856.04
        },
        {
            "timestamp": 1771385437,
            "date": "2026-02-18T03:30:37+00:00",
            "price": 1858.03
        },
        {
            "timestamp": 1771386336,
            "date": "2026-02-18T03:45:36+00:00",
            "price": 1858.59
        },
        {
            "timestamp": 1771387237,
            "date": "2026-02-18T04:00:37+00:00",
            "price": 1858.03
        },
        {
            "timestamp": 1771388136,
            "date": "2026-02-18T04:15:36+00:00",
            "price": 1858.88
        },
        {
            "timestamp": 1771389037,
            "date": "2026-02-18T04:30:37+00:00",
            "price": 1867.1
        },
        {
            "timestamp": 1771389937,
            "date": "2026-02-18T04:45:37+00:00",
            "price": 1873.62
        },
        {
            "timestamp": 1771390838,
            "date": "2026-02-18T05:00:38+00:00",
            "price": 1867.38
        },
        {
            "timestamp": 1771391737,
            "date": "2026-02-18T05:15:37+00:00",
            "price": 1878.15
        },
        {
            "timestamp": 1771392637,
            "date": "2026-02-18T05:30:37+00:00",
            "price": 1873.62
        },
        {
            "timestamp": 1771393536,
            "date": "2026-02-18T05:45:36+00:00",
            "price": 1875.04
        },
        {
            "timestamp": 1771394438,
            "date": "2026-02-18T06:00:38+00:00",
            "price": 1881.56
        },
        {
            "timestamp": 1771395337,
            "date": "2026-02-18T06:15:37+00:00",
            "price": 1882.12
        },
        {
            "timestamp": 1771396237,
            "date": "2026-02-18T06:30:37+00:00",
            "price": 1883.82
        },
        {
            "timestamp": 1771397136,
            "date": "2026-02-18T06:45:36+00:00",
            "price": 1882.69
        },
        {
            "timestamp": 1771398037,
            "date": "2026-02-18T07:00:37+00:00",
            "price": 1882.69
        },
        {
            "timestamp": 1771398937,
            "date": "2026-02-18T07:15:37+00:00",
            "price": 1883.26
        },
        {
            "timestamp": 1771399837,
            "date": "2026-02-18T07:30:37+00:00",
            "price": 1882.69
        },
        {
            "timestamp": 1771400737,
            "date": "2026-02-18T07:45:37+00:00",
            "price": 1882.12
        },
        {
            "timestamp": 1771401637,
            "date": "2026-02-18T08:00:37+00:00",
            "price": 1882.69
        },
        {
            "timestamp": 1771402537,
            "date": "2026-02-18T08:15:37+00:00",
            "price": 1881.56
        },
        {
            "timestamp": 1771403437,
            "date": "2026-02-18T08:30:37+00:00",
            "price": 1867.95
        },
        {
            "timestamp": 1771404337,
            "date": "2026-02-18T08:45:37+00:00",
            "price": 1864.55
        },
        {
            "timestamp": 1771405237,
            "date": "2026-02-18T09:00:37+00:00",
            "price": 1866.53
        },
        {
            "timestamp": 1771406136,
            "date": "2026-02-18T09:15:36+00:00",
            "price": 1869.93
        },
        {
            "timestamp": 1771407037,
            "date": "2026-02-18T09:30:37+00:00",
            "price": 1867.38
        },
        {
            "timestamp": 1771407938,
            "date": "2026-02-18T09:45:38+00:00",
            "price": 1874.47
        },
        {
            "timestamp": 1771408837,
            "date": "2026-02-18T10:00:37+00:00",
            "price": 1874.47
        },
        {
            "timestamp": 1771409737,
            "date": "2026-02-18T10:15:37+00:00",
            "price": 1875.6
        },
        {
            "timestamp": 1771410637,
            "date": "2026-02-18T10:30:37+00:00",
            "price": 1877.3
        },
        {
            "timestamp": 1771411537,
            "date": "2026-02-18T10:45:37+00:00",
            "price": 1877.87
        },
        {
            "timestamp": 1771412438,
            "date": "2026-02-18T11:00:38+00:00",
            "price": 1871.92
        },
        {
            "timestamp": 1771413337,
            "date": "2026-02-18T11:15:37+00:00",
            "price": 1874.47
        },
        {
            "timestamp": 1771414238,
            "date": "2026-02-18T11:30:38+00:00",
            "price": 1873.33
        },
        {
            "timestamp": 1771415137,
            "date": "2026-02-18T11:45:37+00:00",
            "price": 1874.47
        },
        {
            "timestamp": 1771416037,
            "date": "2026-02-18T12:00:37+00:00",
            "price": 1875.04
        },
        {
            "timestamp": 1771416937,
            "date": "2026-02-18T12:15:37+00:00",
            "price": 1869.93
        },
        {
            "timestamp": 1771417837,
            "date": "2026-02-18T12:30:37+00:00",
            "price": 1867.38
        },
        {
            "timestamp": 1771418737,
            "date": "2026-02-18T12:45:37+00:00",
            "price": 1866.53
        },
        {
            "timestamp": 1771419637,
            "date": "2026-02-18T13:00:37+00:00",
            "price": 1866.81
        },
        {
            "timestamp": 1771420537,
            "date": "2026-02-18T13:15:37+00:00",
            "price": 1866.81
        },
        {
            "timestamp": 1771421437,
            "date": "2026-02-18T13:30:37+00:00",
            "price": 1866.81
        },
        {
            "timestamp": 1771422337,
            "date": "2026-02-18T13:45:37+00:00",
            "price": 1881.56
        },
        {
            "timestamp": 1771423238,
            "date": "2026-02-18T14:00:38+00:00",
            "price": 1879.57
        },
        {
            "timestamp": 1771424137,
            "date": "2026-02-18T14:15:37+00:00",
            "price": 1881.56
        },
        {
            "timestamp": 1771425037,
            "date": "2026-02-18T14:30:37+00:00",
            "price": 1879
        },
        {
            "timestamp": 1771425937,
            "date": "2026-02-18T14:45:37+00:00",
            "price": 1885.24
        },
        {
            "timestamp": 1771426838,
            "date": "2026-02-18T15:00:38+00:00",
            "price": 1896.87
        },
        {
            "timestamp": 1771427737,
            "date": "2026-02-18T15:15:37+00:00",
            "price": 1921.53
        },
        {
            "timestamp": 1771428638,
            "date": "2026-02-18T15:30:38+00:00",
            "price": 1922.38
        },
        {
            "timestamp": 1771429537,
            "date": "2026-02-18T15:45:37+00:00",
            "price": 1918.41
        },
        {
            "timestamp": 1771430437,
            "date": "2026-02-18T16:00:37+00:00",
            "price": 1908.49
        },
        {
            "timestamp": 1771431337,
            "date": "2026-02-18T16:15:37+00:00",
            "price": 1905.37
        },
        {
            "timestamp": 1771432238,
            "date": "2026-02-18T16:30:38+00:00",
            "price": 1901.12
        },
        {
            "timestamp": 1771433137,
            "date": "2026-02-18T16:45:37+00:00",
            "price": 1903.95
        },
        {
            "timestamp": 1771434038,
            "date": "2026-02-18T17:00:38+00:00",
            "price": 1907.35
        },
        {
            "timestamp": 1771434937,
            "date": "2026-02-18T17:15:37+00:00",
            "price": 1907.35
        },
        {
            "timestamp": 1771435837,
            "date": "2026-02-18T17:30:37+00:00",
            "price": 1914.44
        },
        {
            "timestamp": 1771436738,
            "date": "2026-02-18T17:45:38+00:00",
            "price": 1915.58
        },
        {
            "timestamp": 1771437638,
            "date": "2026-02-18T18:00:38+00:00",
            "price": 1913.02
        },
        {
            "timestamp": 1771438537,
            "date": "2026-02-18T18:15:37+00:00",
            "price": 1915.58
        },
        {
            "timestamp": 1771439437,
            "date": "2026-02-18T18:30:37+00:00",
            "price": 1915.58
        },
        {
            "timestamp": 1771440338,
            "date": "2026-02-18T18:45:38+00:00",
            "price": 1918.13
        },
        {
            "timestamp": 1771441237,
            "date": "2026-02-18T19:00:37+00:00",
            "price": 1920.96
        },
        {
            "timestamp": 1771442137,
            "date": "2026-02-18T19:15:37+00:00",
            "price": 1919.54
        },
        {
            "timestamp": 1771443040,
            "date": "2026-02-18T19:30:40+00:00",
            "price": 1921.25
        },
        {
            "timestamp": 1771443937,
            "date": "2026-02-18T19:45:37+00:00",
            "price": 1906.5
        },
        {
            "timestamp": 1771444837,
            "date": "2026-02-18T20:00:37+00:00",
            "price": 1907.64
        },
        {
            "timestamp": 1771445737,
            "date": "2026-02-18T20:15:37+00:00",
            "price": 1902.53
        },
        {
            "timestamp": 1771446638,
            "date": "2026-02-18T20:30:38+00:00",
            "price": 1902.25
        },
        {
            "timestamp": 1771447537,
            "date": "2026-02-18T20:45:37+00:00",
            "price": 1903.95
        },
        {
            "timestamp": 1771448438,
            "date": "2026-02-18T21:00:38+00:00",
            "price": 1911.32
        },
        {
            "timestamp": 1771449337,
            "date": "2026-02-18T21:15:37+00:00",
            "price": 1906.79
        },
        {
            "timestamp": 1771450238,
            "date": "2026-02-18T21:30:38+00:00",
            "price": 1901.4
        },
        {
            "timestamp": 1771451137,
            "date": "2026-02-18T21:45:37+00:00",
            "price": 1908.77
        },
        {
            "timestamp": 1771452037,
            "date": "2026-02-18T22:00:37+00:00",
            "price": 1904.8
        },
        {
            "timestamp": 1771452939,
            "date": "2026-02-18T22:15:39+00:00",
            "price": 1907.92
        },
        {
            "timestamp": 1771453837,
            "date": "2026-02-18T22:30:37+00:00",
            "price": 1903.1
        },
        {
            "timestamp": 1771454736,
            "date": "2026-02-18T22:45:36+00:00",
            "price": 1901.97
        },
        {
            "timestamp": 1771455637,
            "date": "2026-02-18T23:00:37+00:00",
            "price": 1906.5
        },
        {
            "timestamp": 1771456539,
            "date": "2026-02-18T23:15:39+00:00",
            "price": 1906.22
        },
        {
            "timestamp": 1771457438,
            "date": "2026-02-18T23:30:38+00:00",
            "price": 1908.77
        },
        {
            "timestamp": 1771458337,
            "date": "2026-02-18T23:45:37+00:00",
            "price": 1908.2
        },
        {
            "timestamp": 1771459270,
            "date": "2026-02-19T00:01:10+00:00",
            "price": 1902.53
        },
        {
            "timestamp": 1771460137,
            "date": "2026-02-19T00:15:37+00:00",
            "price": 1900.83
        },
        {
            "timestamp": 1771461037,
            "date": "2026-02-19T00:30:37+00:00",
            "price": 1902.82
        },
        {
            "timestamp": 1771461937,
            "date": "2026-02-19T00:45:37+00:00",
            "price": 1904.52
        },
        {
            "timestamp": 1771462837,
            "date": "2026-02-19T01:00:37+00:00",
            "price": 1905.65
        },
        {
            "timestamp": 1771463737,
            "date": "2026-02-19T01:15:37+00:00",
            "price": 1902.25
        },
        {
            "timestamp": 1771464637,
            "date": "2026-02-19T01:30:37+00:00",
            "price": 1905.09
        },
        {
            "timestamp": 1771465536,
            "date": "2026-02-19T01:45:36+00:00",
            "price": 1903.67
        },
        {
            "timestamp": 1771466438,
            "date": "2026-02-19T02:00:38+00:00",
            "price": 1899.98
        },
        {
            "timestamp": 1771467338,
            "date": "2026-02-19T02:15:38+00:00",
            "price": 1906.22
        },
        {
            "timestamp": 1771468237,
            "date": "2026-02-19T02:30:37+00:00",
            "price": 1905.09
        },
        {
            "timestamp": 1771469137,
            "date": "2026-02-19T02:45:37+00:00",
            "price": 1906.79
        },
        {
            "timestamp": 1771470038,
            "date": "2026-02-19T03:00:38+00:00",
            "price": 1902.82
        },
        {
            "timestamp": 1771470937,
            "date": "2026-02-19T03:15:37+00:00",
            "price": 1904.8
        },
        {
            "timestamp": 1771471837,
            "date": "2026-02-19T03:30:37+00:00",
            "price": 1907.07
        },
        {
            "timestamp": 1771472737,
            "date": "2026-02-19T03:45:37+00:00",
            "price": 1907.07
        },
        {
            "timestamp": 1771473637,
            "date": "2026-02-19T04:00:37+00:00",
            "price": 1906.79
        },
        {
            "timestamp": 1771474536,
            "date": "2026-02-19T04:15:36+00:00",
            "price": 1904.52
        },
        {
            "timestamp": 1771475437,
            "date": "2026-02-19T04:30:37+00:00",
            "price": 1904.8
        },
        {
            "timestamp": 1771476337,
            "date": "2026-02-19T04:45:37+00:00",
            "price": 1904.24
        },
        {
            "timestamp": 1771477237,
            "date": "2026-02-19T05:00:37+00:00",
            "price": 1901.68
        },
        {
            "timestamp": 1771478137,
            "date": "2026-02-19T05:15:37+00:00",
            "price": 1901.68
        },
        {
            "timestamp": 1771479037,
            "date": "2026-02-19T05:30:37+00:00",
            "price": 1904.8
        },
        {
            "timestamp": 1771479937,
            "date": "2026-02-19T05:45:37+00:00",
            "price": 1902.25
        },
        {
            "timestamp": 1771480837,
            "date": "2026-02-19T06:00:37+00:00",
            "price": 1901.97
        },
        {
            "timestamp": 1771481737,
            "date": "2026-02-19T06:15:37+00:00",
            "price": 1907.07
        },
        {
            "timestamp": 1771482637,
            "date": "2026-02-19T06:30:37+00:00",
            "price": 1911.89
        },
        {
            "timestamp": 1771483537,
            "date": "2026-02-19T06:45:37+00:00",
            "price": 1912.17
        },
        {
            "timestamp": 1771484437,
            "date": "2026-02-19T07:00:37+00:00",
            "price": 1911.61
        },
        {
            "timestamp": 1771485337,
            "date": "2026-02-19T07:15:37+00:00",
            "price": 1914.73
        },
        {
            "timestamp": 1771486237,
            "date": "2026-02-19T07:30:37+00:00",
            "price": 1916.71
        },
        {
            "timestamp": 1771487136,
            "date": "2026-02-19T07:45:36+00:00",
            "price": 1916.71
        },
        {
            "timestamp": 1771488037,
            "date": "2026-02-19T08:00:37+00:00",
            "price": 1918.98
        },
        {
            "timestamp": 1771488937,
            "date": "2026-02-19T08:15:37+00:00",
            "price": 1916.71
        },
        {
            "timestamp": 1771489837,
            "date": "2026-02-19T08:30:37+00:00",
            "price": 1931.17
        },
        {
            "timestamp": 1771490738,
            "date": "2026-02-19T08:45:38+00:00",
            "price": 1928.05
        },
        {
            "timestamp": 1771491637,
            "date": "2026-02-19T09:00:37+00:00",
            "price": 1920.11
        },
        {
            "timestamp": 1771492537,
            "date": "2026-02-19T09:15:37+00:00",
            "price": 1920.96
        },
        {
            "timestamp": 1771493437,
            "date": "2026-02-19T09:30:37+00:00",
            "price": 1919.83
        },
        {
            "timestamp": 1771494338,
            "date": "2026-02-19T09:45:38+00:00",
            "price": 1919.83
        },
        {
            "timestamp": 1771495237,
            "date": "2026-02-19T10:00:37+00:00",
            "price": 1916.71
        },
        {
            "timestamp": 1771496137,
            "date": "2026-02-19T10:15:37+00:00",
            "price": 1915.86
        },
        {
            "timestamp": 1771497037,
            "date": "2026-02-19T10:30:37+00:00",
            "price": 1915.86
        },
        {
            "timestamp": 1771497937,
            "date": "2026-02-19T10:45:37+00:00",
            "price": 1917.84
        },
        {
            "timestamp": 1771498837,
            "date": "2026-02-19T11:00:37+00:00",
            "price": 1915.29
        },
        {
            "timestamp": 1771499737,
            "date": "2026-02-19T11:15:37+00:00",
            "price": 1918.41
        },
        {
            "timestamp": 1771500637,
            "date": "2026-02-19T11:30:37+00:00",
            "price": 1917.28
        },
        {
            "timestamp": 1771501537,
            "date": "2026-02-19T11:45:37+00:00",
            "price": 1911.61
        },
        {
            "timestamp": 1771502437,
            "date": "2026-02-19T12:00:37+00:00",
            "price": 1913.02
        },
        {
            "timestamp": 1771503337,
            "date": "2026-02-19T12:15:37+00:00",
            "price": 1903.67
        },
        {
            "timestamp": 1771504237,
            "date": "2026-02-19T12:30:37+00:00",
            "price": 1901.68
        },
        {
            "timestamp": 1771505137,
            "date": "2026-02-19T12:45:37+00:00",
            "price": 1890.06
        },
        {
            "timestamp": 1771506037,
            "date": "2026-02-19T13:00:37+00:00",
            "price": 1897.15
        },
        {
            "timestamp": 1771506937,
            "date": "2026-02-19T13:15:37+00:00",
            "price": 1898
        },
        {
            "timestamp": 1771507837,
            "date": "2026-02-19T13:30:37+00:00",
            "price": 1891.2
        },
        {
            "timestamp": 1771508737,
            "date": "2026-02-19T13:45:37+00:00",
            "price": 1888.93
        },
        {
            "timestamp": 1771509638,
            "date": "2026-02-19T14:00:38+00:00",
            "price": 1897.72
        },
        {
            "timestamp": 1771510538,
            "date": "2026-02-19T14:15:38+00:00",
            "price": 1899.42
        },
        {
            "timestamp": 1771511437,
            "date": "2026-02-19T14:30:37+00:00",
            "price": 1895.16
        },
        {
            "timestamp": 1771512337,
            "date": "2026-02-19T14:45:37+00:00",
            "price": 1891.76
        },
        {
            "timestamp": 1771513238,
            "date": "2026-02-19T15:00:38+00:00",
            "price": 1902.25
        },
        {
            "timestamp": 1771514138,
            "date": "2026-02-19T15:15:38+00:00",
            "price": 1900.83
        },
        {
            "timestamp": 1771515038,
            "date": "2026-02-19T15:30:38+00:00",
            "price": 1903.39
        },
        {
            "timestamp": 1771515938,
            "date": "2026-02-19T15:45:38+00:00",
            "price": 1904.24
        },
        {
            "timestamp": 1771516837,
            "date": "2026-02-19T16:00:37+00:00",
            "price": 1910.19
        },
        {
            "timestamp": 1771517737,
            "date": "2026-02-19T16:15:37+00:00",
            "price": 1914.73
        },
        {
            "timestamp": 1771518639,
            "date": "2026-02-19T16:30:39+00:00",
            "price": 1908.77
        },
        {
            "timestamp": 1771519537,
            "date": "2026-02-19T16:45:37+00:00",
            "price": 1911.04
        },
        {
            "timestamp": 1771520437,
            "date": "2026-02-19T17:00:37+00:00",
            "price": 1907.64
        },
        {
            "timestamp": 1771521339,
            "date": "2026-02-19T17:15:39+00:00",
            "price": 1898.85
        },
        {
            "timestamp": 1771522238,
            "date": "2026-02-19T17:30:38+00:00",
            "price": 1885.81
        },
        {
            "timestamp": 1771523137,
            "date": "2026-02-19T17:45:37+00:00",
            "price": 1892.05
        },
        {
            "timestamp": 1771524039,
            "date": "2026-02-19T18:00:39+00:00",
            "price": 1893.18
        },
        {
            "timestamp": 1771524937,
            "date": "2026-02-19T18:15:37+00:00",
            "price": 1880.42
        },
        {
            "timestamp": 1771525838,
            "date": "2026-02-19T18:30:38+00:00",
            "price": 1884.67
        },
        {
            "timestamp": 1771526737,
            "date": "2026-02-19T18:45:37+00:00",
            "price": 1885.81
        },
        {
            "timestamp": 1771527638,
            "date": "2026-02-19T19:00:38+00:00",
            "price": 1887.79
        },
        {
            "timestamp": 1771528537,
            "date": "2026-02-19T19:15:37+00:00",
            "price": 1884.96
        },
        {
            "timestamp": 1771529437,
            "date": "2026-02-19T19:30:37+00:00",
            "price": 1892.33
        },
        {
            "timestamp": 1771530337,
            "date": "2026-02-19T19:45:37+00:00",
            "price": 1887.79
        },
        {
            "timestamp": 1771531238,
            "date": "2026-02-19T20:00:38+00:00",
            "price": 1888.36
        },
        {
            "timestamp": 1771532139,
            "date": "2026-02-19T20:15:39+00:00",
            "price": 1888.64
        },
        {
            "timestamp": 1771533037,
            "date": "2026-02-19T20:30:37+00:00",
            "price": 1888.64
        },
        {
            "timestamp": 1771533937,
            "date": "2026-02-19T20:45:37+00:00",
            "price": 1897.72
        },
        {
            "timestamp": 1771534837,
            "date": "2026-02-19T21:00:37+00:00",
            "price": 1896.58
        },
        {
            "timestamp": 1771535738,
            "date": "2026-02-19T21:15:38+00:00",
            "price": 1900.83
        },
        {
            "timestamp": 1771536637,
            "date": "2026-02-19T21:30:37+00:00",
            "price": 1898
        },
        {
            "timestamp": 1771537539,
            "date": "2026-02-19T21:45:39+00:00",
            "price": 1898.85
        },
        {
            "timestamp": 1771538437,
            "date": "2026-02-19T22:00:37+00:00",
            "price": 1896.87
        },
        {
            "timestamp": 1771539337,
            "date": "2026-02-19T22:15:37+00:00",
            "price": 1895.73
        },
        {
            "timestamp": 1771540237,
            "date": "2026-02-19T22:30:37+00:00",
            "price": 1898
        },
        {
            "timestamp": 1771541137,
            "date": "2026-02-19T22:45:37+00:00",
            "price": 1907.35
        },
        {
            "timestamp": 1771542037,
            "date": "2026-02-19T23:00:37+00:00",
            "price": 1910.47
        },
        {
            "timestamp": 1771542936,
            "date": "2026-02-19T23:15:36+00:00",
            "price": 1910.76
        },
        {
            "timestamp": 1771543837,
            "date": "2026-02-19T23:30:37+00:00",
            "price": 1894.88
        },
        {
            "timestamp": 1771544737,
            "date": "2026-02-19T23:45:37+00:00",
            "price": 1895.16
        },
        {
            "timestamp": 1771545670,
            "date": "2026-02-20T00:01:10+00:00",
            "price": 1891.2
        },
        {
            "timestamp": 1771546540,
            "date": "2026-02-20T00:15:40+00:00",
            "price": 1894.31
        },
        {
            "timestamp": 1771547437,
            "date": "2026-02-20T00:30:37+00:00",
            "price": 1897.15
        },
        {
            "timestamp": 1771548337,
            "date": "2026-02-20T00:45:37+00:00",
            "price": 1901.12
        },
        {
            "timestamp": 1771549237,
            "date": "2026-02-20T01:00:37+00:00",
            "price": 1894.6
        },
        {
            "timestamp": 1771550137,
            "date": "2026-02-20T01:15:37+00:00",
            "price": 1898.28
        },
        {
            "timestamp": 1771551037,
            "date": "2026-02-20T01:30:37+00:00",
            "price": 1898
        },
        {
            "timestamp": 1771551937,
            "date": "2026-02-20T01:45:37+00:00",
            "price": 1900.27
        },
        {
            "timestamp": 1771552837,
            "date": "2026-02-20T02:00:37+00:00",
            "price": 1892.61
        },
        {
            "timestamp": 1771553738,
            "date": "2026-02-20T02:15:38+00:00",
            "price": 1892.61
        },
        {
            "timestamp": 1771554637,
            "date": "2026-02-20T02:30:37+00:00",
            "price": 1898.57
        },
        {
            "timestamp": 1771555537,
            "date": "2026-02-20T02:45:37+00:00",
            "price": 1899.7
        },
        {
            "timestamp": 1771556438,
            "date": "2026-02-20T03:00:38+00:00",
            "price": 1893.75
        },
        {
            "timestamp": 1771557336,
            "date": "2026-02-20T03:15:36+00:00",
            "price": 1893.75
        },
        {
            "timestamp": 1771558237,
            "date": "2026-02-20T03:30:37+00:00",
            "price": 1890.63
        },
        {
            "timestamp": 1771559137,
            "date": "2026-02-20T03:45:37+00:00",
            "price": 1892.05
        },
        {
            "timestamp": 1771560039,
            "date": "2026-02-20T04:00:39+00:00",
            "price": 1890.63
        },
        {
            "timestamp": 1771560937,
            "date": "2026-02-20T04:15:37+00:00",
            "price": 1890.63
        },
        {
            "timestamp": 1771561837,
            "date": "2026-02-20T04:30:37+00:00",
            "price": 1889.78
        },
        {
            "timestamp": 1771562736,
            "date": "2026-02-20T04:45:36+00:00",
            "price": 1892.33
        },
        {
            "timestamp": 1771563637,
            "date": "2026-02-20T05:00:37+00:00",
            "price": 1891.2
        },
        {
            "timestamp": 1771564537,
            "date": "2026-02-20T05:15:37+00:00",
            "price": 1894.03
        },
        {
            "timestamp": 1771565437,
            "date": "2026-02-20T05:30:37+00:00",
            "price": 1894.03
        },
        {
            "timestamp": 1771566337,
            "date": "2026-02-20T05:45:37+00:00",
            "price": 1892.05
        },
        {
            "timestamp": 1771567238,
            "date": "2026-02-20T06:00:38+00:00",
            "price": 1892.61
        },
        {
            "timestamp": 1771568137,
            "date": "2026-02-20T06:15:37+00:00",
            "price": 1892.9
        },
        {
            "timestamp": 1771569037,
            "date": "2026-02-20T06:30:37+00:00",
            "price": 1907.64
        },
        {
            "timestamp": 1771569937,
            "date": "2026-02-20T06:45:37+00:00",
            "price": 1905.37
        },
        {
            "timestamp": 1771570837,
            "date": "2026-02-20T07:00:37+00:00",
            "price": 1899.7
        },
        {
            "timestamp": 1771571736,
            "date": "2026-02-20T07:15:36+00:00",
            "price": 1903.39
        },
        {
            "timestamp": 1771572637,
            "date": "2026-02-20T07:30:37+00:00",
            "price": 1903.95
        },
        {
            "timestamp": 1771573537,
            "date": "2026-02-20T07:45:37+00:00",
            "price": 1907.35
        },
        {
            "timestamp": 1771574438,
            "date": "2026-02-20T08:00:38+00:00",
            "price": 1891.2
        },
        {
            "timestamp": 1771575337,
            "date": "2026-02-20T08:15:37+00:00",
            "price": 1891.48
        },
        {
            "timestamp": 1771576237,
            "date": "2026-02-20T08:30:37+00:00",
            "price": 1904.52
        },
        {
            "timestamp": 1771577136,
            "date": "2026-02-20T08:45:36+00:00",
            "price": 1912.46
        },
        {
            "timestamp": 1771578037,
            "date": "2026-02-20T09:00:37+00:00",
            "price": 1912.74
        },
        {
            "timestamp": 1771578937,
            "date": "2026-02-20T09:15:37+00:00",
            "price": 1927.48
        },
        {
            "timestamp": 1771579837,
            "date": "2026-02-20T09:30:37+00:00",
            "price": 1930.32
        },
        {
            "timestamp": 1771580737,
            "date": "2026-02-20T09:45:37+00:00",
            "price": 1928.05
        },
        {
            "timestamp": 1771581638,
            "date": "2026-02-20T10:00:38+00:00",
            "price": 1932.02
        },
        {
            "timestamp": 1771582537,
            "date": "2026-02-20T10:15:37+00:00",
            "price": 1936.55
        },
        {
            "timestamp": 1771583437,
            "date": "2026-02-20T10:30:37+00:00",
            "price": 1928.05
        },
        {
            "timestamp": 1771584337,
            "date": "2026-02-20T10:45:37+00:00",
            "price": 1938.54
        },
        {
            "timestamp": 1771585237,
            "date": "2026-02-20T11:00:37+00:00",
            "price": 1925.5
        },
        {
            "timestamp": 1771586137,
            "date": "2026-02-20T11:15:37+00:00",
            "price": 1927.48
        },
        {
            "timestamp": 1771587037,
            "date": "2026-02-20T11:30:37+00:00",
            "price": 1931.45
        },
        {
            "timestamp": 1771587937,
            "date": "2026-02-20T11:45:37+00:00",
            "price": 1931.17
        },
        {
            "timestamp": 1771588837,
            "date": "2026-02-20T12:00:37+00:00",
            "price": 1928.05
        },
        {
            "timestamp": 1771589737,
            "date": "2026-02-20T12:15:37+00:00",
            "price": 1931.45
        },
        {
            "timestamp": 1771590638,
            "date": "2026-02-20T12:30:38+00:00",
            "price": 1928.05
        },
        {
            "timestamp": 1771591537,
            "date": "2026-02-20T12:45:37+00:00",
            "price": 1928.05
        },
        {
            "timestamp": 1771592437,
            "date": "2026-02-20T13:00:37+00:00",
            "price": 1926.92
        },
        {
            "timestamp": 1771593337,
            "date": "2026-02-20T13:15:37+00:00",
            "price": 1937.69
        },
        {
            "timestamp": 1771594237,
            "date": "2026-02-20T13:30:37+00:00",
            "price": 1935.42
        },
        {
            "timestamp": 1771595137,
            "date": "2026-02-20T13:45:37+00:00",
            "price": 1937.4
        },
        {
            "timestamp": 1771596037,
            "date": "2026-02-20T14:00:37+00:00",
            "price": 1929.75
        },
        {
            "timestamp": 1771596937,
            "date": "2026-02-20T14:15:37+00:00",
            "price": 1931.45
        },
        {
            "timestamp": 1771597837,
            "date": "2026-02-20T14:30:37+00:00",
            "price": 1939.11
        },
        {
            "timestamp": 1771598737,
            "date": "2026-02-20T14:45:37+00:00",
            "price": 1944.78
        },
        {
            "timestamp": 1771599637,
            "date": "2026-02-20T15:00:37+00:00",
            "price": 1947.04
        },
        {
            "timestamp": 1771600537,
            "date": "2026-02-20T15:15:37+00:00",
            "price": 1944.21
        },
        {
            "timestamp": 1771601437,
            "date": "2026-02-20T15:30:37+00:00",
            "price": 1941.66
        },
        {
            "timestamp": 1771602337,
            "date": "2026-02-20T15:45:37+00:00",
            "price": 1945.91
        },
        {
            "timestamp": 1771603238,
            "date": "2026-02-20T16:00:38+00:00",
            "price": 1946.48
        },
        {
            "timestamp": 1771604137,
            "date": "2026-02-20T16:15:37+00:00",
            "price": 1944.21
        },
        {
            "timestamp": 1771605037,
            "date": "2026-02-20T16:30:37+00:00",
            "price": 1945.06
        },
        {
            "timestamp": 1771605938,
            "date": "2026-02-20T16:45:38+00:00",
            "price": 1947.61
        },
        {
            "timestamp": 1771606838,
            "date": "2026-02-20T17:00:38+00:00",
            "price": 1947.61
        },
        {
            "timestamp": 1771607737,
            "date": "2026-02-20T17:15:37+00:00",
            "price": 1976.24
        },
        {
            "timestamp": 1771608637,
            "date": "2026-02-20T17:30:37+00:00",
            "price": 1963.77
        },
        {
            "timestamp": 1771609537,
            "date": "2026-02-20T17:45:37+00:00",
            "price": 1963.77
        },
        {
            "timestamp": 1771610438,
            "date": "2026-02-20T18:00:38+00:00",
            "price": 1960.37
        },
        {
            "timestamp": 1771611336,
            "date": "2026-02-20T18:15:36+00:00",
            "price": 1963.77
        },
        {
            "timestamp": 1771612237,
            "date": "2026-02-20T18:30:37+00:00",
            "price": 1964.62
        },
        {
            "timestamp": 1771613137,
            "date": "2026-02-20T18:45:37+00:00",
            "price": 1970.29
        },
        {
            "timestamp": 1771614037,
            "date": "2026-02-20T19:00:37+00:00",
            "price": 1969.72
        },
        {
            "timestamp": 1771614937,
            "date": "2026-02-20T19:15:37+00:00",
            "price": 1971.99
        },
        {
            "timestamp": 1771615838,
            "date": "2026-02-20T19:30:38+00:00",
            "price": 1970.01
        },
        {
            "timestamp": 1771616737,
            "date": "2026-02-20T19:45:37+00:00",
            "price": 1970.29
        },
        {
            "timestamp": 1771617637,
            "date": "2026-02-20T20:00:37+00:00",
            "price": 1967.17
        },
        {
            "timestamp": 1771618537,
            "date": "2026-02-20T20:15:37+00:00",
            "price": 1971.71
        },
        {
            "timestamp": 1771619437,
            "date": "2026-02-20T20:30:37+00:00",
            "price": 1981.06
        },
        {
            "timestamp": 1771620337,
            "date": "2026-02-20T20:45:37+00:00",
            "price": 1970.57
        },
        {
            "timestamp": 1771621237,
            "date": "2026-02-20T21:00:37+00:00",
            "price": 1971.42
        },
        {
            "timestamp": 1771622139,
            "date": "2026-02-20T21:15:39+00:00",
            "price": 1974.54
        },
        {
            "timestamp": 1771623037,
            "date": "2026-02-20T21:30:37+00:00",
            "price": 1973.41
        },
        {
            "timestamp": 1771623938,
            "date": "2026-02-20T21:45:38+00:00",
            "price": 1973.41
        },
        {
            "timestamp": 1771624837,
            "date": "2026-02-20T22:00:37+00:00",
            "price": 1973.41
        },
        {
            "timestamp": 1771625736,
            "date": "2026-02-20T22:15:36+00:00",
            "price": 1973.41
        },
        {
            "timestamp": 1771626637,
            "date": "2026-02-20T22:30:37+00:00",
            "price": 1973.41
        },
        {
            "timestamp": 1771627536,
            "date": "2026-02-20T22:45:36+00:00",
            "price": 1973.41
        },
        {
            "timestamp": 1771628437,
            "date": "2026-02-20T23:00:37+00:00",
            "price": 1973.41
        },
        {
            "timestamp": 1771629336,
            "date": "2026-02-20T23:15:36+00:00",
            "price": 1973.41
        },
        {
            "timestamp": 1771630237,
            "date": "2026-02-20T23:30:37+00:00",
            "price": 1973.41
        },
        {
            "timestamp": 1771631137,
            "date": "2026-02-20T23:45:37+00:00",
            "price": 1973.41
        },
        {
            "timestamp": 1771632069,
            "date": "2026-02-21T00:01:09+00:00",
            "price": 1973.41
        },
        {
            "timestamp": 1771632937,
            "date": "2026-02-21T00:15:37+00:00",
            "price": 1973.41
        },
        {
            "timestamp": 1771633837,
            "date": "2026-02-21T00:30:37+00:00",
            "price": 1973.41
        },
        {
            "timestamp": 1771634737,
            "date": "2026-02-21T00:45:37+00:00",
            "price": 1973.41
        },
        {
            "timestamp": 1771635637,
            "date": "2026-02-21T01:00:37+00:00",
            "price": 1973.41
        },
        {
            "timestamp": 1771636537,
            "date": "2026-02-21T01:15:37+00:00",
            "price": 1973.41
        },
        {
            "timestamp": 1771637437,
            "date": "2026-02-21T01:30:37+00:00",
            "price": 1973.41
        },
        {
            "timestamp": 1771638337,
            "date": "2026-02-21T01:45:37+00:00",
            "price": 1973.41
        },
        {
            "timestamp": 1771639238,
            "date": "2026-02-21T02:00:38+00:00",
            "price": 1973.41
        },
        {
            "timestamp": 1771640136,
            "date": "2026-02-21T02:15:36+00:00",
            "price": 1973.41
        },
        {
            "timestamp": 1771641037,
            "date": "2026-02-21T02:30:37+00:00",
            "price": 1973.41
        },
        {
            "timestamp": 1771641937,
            "date": "2026-02-21T02:45:37+00:00",
            "price": 1973.41
        },
        {
            "timestamp": 1771642838,
            "date": "2026-02-21T03:00:38+00:00",
            "price": 1973.41
        },
        {
            "timestamp": 1771643737,
            "date": "2026-02-21T03:15:37+00:00",
            "price": 1973.41
        },
        {
            "timestamp": 1771644637,
            "date": "2026-02-21T03:30:37+00:00",
            "price": 1973.41
        },
        {
            "timestamp": 1771645536,
            "date": "2026-02-21T03:45:36+00:00",
            "price": 1973.41
        },
        {
            "timestamp": 1771646437,
            "date": "2026-02-21T04:00:37+00:00",
            "price": 1973.41
        },
        {
            "timestamp": 1771647337,
            "date": "2026-02-21T04:15:37+00:00",
            "price": 1973.41
        },
        {
            "timestamp": 1771648237,
            "date": "2026-02-21T04:30:37+00:00",
            "price": 1973.41
        },
        {
            "timestamp": 1771649137,
            "date": "2026-02-21T04:45:37+00:00",
            "price": 1973.41
        },
        {
            "timestamp": 1771650039,
            "date": "2026-02-21T05:00:39+00:00",
            "price": 1973.41
        },
        {
            "timestamp": 1771650937,
            "date": "2026-02-21T05:15:37+00:00",
            "price": 1973.41
        },
        {
            "timestamp": 1771651837,
            "date": "2026-02-21T05:30:37+00:00",
            "price": 1973.41
        },
        {
            "timestamp": 1771652736,
            "date": "2026-02-21T05:45:36+00:00",
            "price": 1973.41
        },
        {
            "timestamp": 1771653637,
            "date": "2026-02-21T06:00:37+00:00",
            "price": 1973.41
        },
        {
            "timestamp": 1771654537,
            "date": "2026-02-21T06:15:37+00:00",
            "price": 1973.41
        },
        {
            "timestamp": 1771655438,
            "date": "2026-02-21T06:30:38+00:00",
            "price": 1973.41
        },
        {
            "timestamp": 1771656336,
            "date": "2026-02-21T06:45:36+00:00",
            "price": 1973.41
        },
        {
            "timestamp": 1771657237,
            "date": "2026-02-21T07:00:37+00:00",
            "price": 1973.41
        },
        {
            "timestamp": 1771658138,
            "date": "2026-02-21T07:15:38+00:00",
            "price": 1973.41
        },
        {
            "timestamp": 1771659037,
            "date": "2026-02-21T07:30:37+00:00",
            "price": 1973.41
        },
        {
            "timestamp": 1771659937,
            "date": "2026-02-21T07:45:37+00:00",
            "price": 1973.41
        },
        {
            "timestamp": 1771660837,
            "date": "2026-02-21T08:00:37+00:00",
            "price": 1973.41
        },
        {
            "timestamp": 1771661737,
            "date": "2026-02-21T08:15:37+00:00",
            "price": 1973.41
        },
        {
            "timestamp": 1771662637,
            "date": "2026-02-21T08:30:37+00:00",
            "price": 1973.41
        },
        {
            "timestamp": 1771663536,
            "date": "2026-02-21T08:45:36+00:00",
            "price": 1973.41
        },
        {
            "timestamp": 1771664439,
            "date": "2026-02-21T09:00:39+00:00",
            "price": 1973.41
        },
        {
            "timestamp": 1771665337,
            "date": "2026-02-21T09:15:37+00:00",
            "price": 1973.41
        },
        {
            "timestamp": 1771666239,
            "date": "2026-02-21T09:30:39+00:00",
            "price": 1973.41
        },
        {
            "timestamp": 1771667137,
            "date": "2026-02-21T09:45:37+00:00",
            "price": 1973.41
        },
        {
            "timestamp": 1771668036,
            "date": "2026-02-21T10:00:36+00:00",
            "price": 1973.41
        },
        {
            "timestamp": 1771668937,
            "date": "2026-02-21T10:15:37+00:00",
            "price": 1973.41
        },
        {
            "timestamp": 1771669837,
            "date": "2026-02-21T10:30:37+00:00",
            "price": 1973.41
        },
        {
            "timestamp": 1771670736,
            "date": "2026-02-21T10:45:36+00:00",
            "price": 1973.41
        },
        {
            "timestamp": 1771671637,
            "date": "2026-02-21T11:00:37+00:00",
            "price": 1973.41
        },
        {
            "timestamp": 1771672537,
            "date": "2026-02-21T11:15:37+00:00",
            "price": 1973.41
        },
        {
            "timestamp": 1771673437,
            "date": "2026-02-21T11:30:37+00:00",
            "price": 1973.41
        },
        {
            "timestamp": 1771674336,
            "date": "2026-02-21T11:45:36+00:00",
            "price": 1973.41
        },
        {
            "timestamp": 1771675237,
            "date": "2026-02-21T12:00:37+00:00",
            "price": 1973.41
        },
        {
            "timestamp": 1771676137,
            "date": "2026-02-21T12:15:37+00:00",
            "price": 1973.41
        },
        {
            "timestamp": 1771677037,
            "date": "2026-02-21T12:30:37+00:00",
            "price": 1973.41
        },
        {
            "timestamp": 1771677937,
            "date": "2026-02-21T12:45:37+00:00",
            "price": 1973.41
        },
        {
            "timestamp": 1771678837,
            "date": "2026-02-21T13:00:37+00:00",
            "price": 1973.41
        },
        {
            "timestamp": 1771679737,
            "date": "2026-02-21T13:15:37+00:00",
            "price": 1973.41
        },
        {
            "timestamp": 1771680637,
            "date": "2026-02-21T13:30:37+00:00",
            "price": 1973.41
        },
        {
            "timestamp": 1771681537,
            "date": "2026-02-21T13:45:37+00:00",
            "price": 1973.41
        },
        {
            "timestamp": 1771682437,
            "date": "2026-02-21T14:00:37+00:00",
            "price": 1973.41
        },
        {
            "timestamp": 1771683336,
            "date": "2026-02-21T14:15:36+00:00",
            "price": 1973.41
        },
        {
            "timestamp": 1771684237,
            "date": "2026-02-21T14:30:37+00:00",
            "price": 1973.41
        },
        {
            "timestamp": 1771685137,
            "date": "2026-02-21T14:45:37+00:00",
            "price": 1973.41
        },
        {
            "timestamp": 1771686037,
            "date": "2026-02-21T15:00:37+00:00",
            "price": 1973.41
        },
        {
            "timestamp": 1771686937,
            "date": "2026-02-21T15:15:37+00:00",
            "price": 1973.41
        },
        {
            "timestamp": 1771687838,
            "date": "2026-02-21T15:30:38+00:00",
            "price": 1973.41
        },
        {
            "timestamp": 1771688737,
            "date": "2026-02-21T15:45:37+00:00",
            "price": 1973.41
        },
        {
            "timestamp": 1771689637,
            "date": "2026-02-21T16:00:37+00:00",
            "price": 1973.41
        },
        {
            "timestamp": 1771690537,
            "date": "2026-02-21T16:15:37+00:00",
            "price": 1973.41
        },
        {
            "timestamp": 1771691437,
            "date": "2026-02-21T16:30:37+00:00",
            "price": 1973.41
        },
        {
            "timestamp": 1771692338,
            "date": "2026-02-21T16:45:38+00:00",
            "price": 1973.41
        },
        {
            "timestamp": 1771693237,
            "date": "2026-02-21T17:00:37+00:00",
            "price": 1973.41
        },
        {
            "timestamp": 1771694137,
            "date": "2026-02-21T17:15:37+00:00",
            "price": 1973.41
        },
        {
            "timestamp": 1771695037,
            "date": "2026-02-21T17:30:37+00:00",
            "price": 1973.41
        },
        {
            "timestamp": 1771695936,
            "date": "2026-02-21T17:45:36+00:00",
            "price": 1973.41
        },
        {
            "timestamp": 1771696837,
            "date": "2026-02-21T18:00:37+00:00",
            "price": 1973.41
        },
        {
            "timestamp": 1771697737,
            "date": "2026-02-21T18:15:37+00:00",
            "price": 1973.41
        },
        {
            "timestamp": 1771698637,
            "date": "2026-02-21T18:30:37+00:00",
            "price": 1973.41
        },
        {
            "timestamp": 1771699537,
            "date": "2026-02-21T18:45:37+00:00",
            "price": 1973.41
        },
        {
            "timestamp": 1771700437,
            "date": "2026-02-21T19:00:37+00:00",
            "price": 1973.41
        },
        {
            "timestamp": 1771701337,
            "date": "2026-02-21T19:15:37+00:00",
            "price": 1973.41
        },
        {
            "timestamp": 1771702237,
            "date": "2026-02-21T19:30:37+00:00",
            "price": 1973.41
        },
        {
            "timestamp": 1771703138,
            "date": "2026-02-21T19:45:38+00:00",
            "price": 1973.41
        },
        {
            "timestamp": 1771704038,
            "date": "2026-02-21T20:00:38+00:00",
            "price": 1973.41
        },
        {
            "timestamp": 1771704937,
            "date": "2026-02-21T20:15:37+00:00",
            "price": 1973.41
        },
        {
            "timestamp": 1771705838,
            "date": "2026-02-21T20:30:38+00:00",
            "price": 1973.41
        },
        {
            "timestamp": 1771706736,
            "date": "2026-02-21T20:45:36+00:00",
            "price": 1973.41
        },
        {
            "timestamp": 1771707637,
            "date": "2026-02-21T21:00:37+00:00",
            "price": 1973.41
        },
        {
            "timestamp": 1771708537,
            "date": "2026-02-21T21:15:37+00:00",
            "price": 1973.41
        },
        {
            "timestamp": 1771709437,
            "date": "2026-02-21T21:30:37+00:00",
            "price": 1973.41
        },
        {
            "timestamp": 1771710337,
            "date": "2026-02-21T21:45:37+00:00",
            "price": 1973.41
        },
        {
            "timestamp": 1771711237,
            "date": "2026-02-21T22:00:37+00:00",
            "price": 1973.41
        },
        {
            "timestamp": 1771712138,
            "date": "2026-02-21T22:15:38+00:00",
            "price": 1973.41
        },
        {
            "timestamp": 1771713037,
            "date": "2026-02-21T22:30:37+00:00",
            "price": 1973.41
        },
        {
            "timestamp": 1771713937,
            "date": "2026-02-21T22:45:37+00:00",
            "price": 1973.41
        },
        {
            "timestamp": 1771714837,
            "date": "2026-02-21T23:00:37+00:00",
            "price": 1973.41
        },
        {
            "timestamp": 1771715737,
            "date": "2026-02-21T23:15:37+00:00",
            "price": 1973.41
        },
        {
            "timestamp": 1771716638,
            "date": "2026-02-21T23:30:38+00:00",
            "price": 1973.41
        },
        {
            "timestamp": 1771717538,
            "date": "2026-02-21T23:45:38+00:00",
            "price": 1973.41
        },
        {
            "timestamp": 1771718482,
            "date": "2026-02-22T00:01:22+00:00",
            "price": 1973.41
        },
        {
            "timestamp": 1771719337,
            "date": "2026-02-22T00:15:37+00:00",
            "price": 1973.41
        },
        {
            "timestamp": 1771720238,
            "date": "2026-02-22T00:30:38+00:00",
            "price": 1973.41
        },
        {
            "timestamp": 1771721137,
            "date": "2026-02-22T00:45:37+00:00",
            "price": 1973.41
        },
        {
            "timestamp": 1771722038,
            "date": "2026-02-22T01:00:38+00:00",
            "price": 1973.41
        }
    ],
    "asset": "platinum",
    "timeframe": "recent",
    "days_included": 7,
    "last_updated": "2026-02-22T01:00:38+00:00",
    "entries_count": 676
}